{"videoshark-offcanvas-widget":{"videoshark_recent_posts-2":{"title":"Recent Videos","category":5,"title_size":"entry-title-xsmall","number":5,"orderby":"date","order":"desc","show_date":1,"date_format":"format_2","style":"style_1"}},"videoshark-homepage-bottom-widget":{"videoshark_advanced_recent_widget-2":{"title":"Featured Videos","category":4,"button_text":"View All","image_size":"featured-media-medium","title_size":"entry-title-xsmall","number_of_column":"column-3","number":4,"show_category":0,"show_author":0,"show_date":1,"show_share":1,"show_post_view":1,"date_format":"format_2","bg_color_option":"#1d2127","text_color_option":"#ffffff"},"videoshark_carousel_widget-2":{"title":"Entertainment","category":49,"button_text":"View All","image_size":"featured-media-medium","title_size":"entry-title-xsmall","number":8,"slider_per_view":4,"centered_slides":0,"autoplay":1,"space_between":"30","pagination":1,"show_category":0,"show_author":0,"show_date":1,"show_share":1,"show_post_view":1,"date_format":"format_2","bg_color_option":"#121212","text_color_option":"#a5acb8"}}}